json_structure_digest-0.9.1.data/scripts/json_digest.py
jsondigest/__init__.py
jsondigest/json_digest.py
json_structure_digest-0.9.1.dist-info/LICENSE.txt
json_structure_digest-0.9.1.dist-info/METADATA
json_structure_digest-0.9.1.dist-info/WHEEL
json_structure_digest-0.9.1.dist-info/top_level.txt
json_structure_digest-0.9.1.dist-info/RECORD
