Metadata-Version: 2.1
Name: json-structure-digest
Version: 0.9.1
Summary: A library and tool for calculating consistent digest of a json data string
Home-page: UNKNOWN
Author: Takeshi Kubo
Author-email: 
License: MIT
Platform: UNKNOWN
Classifier: Development Status :: 4 - Beta
Classifier: Programming Language :: Python :: 3.5
Classifier: Programming Language :: Python :: 3.6
Classifier: Programming Language :: Python :: 3.7
Classifier: Topic :: Software Development
